{
    "enabled": true,
    "coin": "meter.json",

    "address": "37KQnNAspu1BsaMQqrTVFBjjDCwon246Z4",

    "rewardRecipients": {
        "37KQnNAspu1BsaMQqrTVFBjjDCwon246Z4": 1.5,
        "37KQnNAspu1BsaMQqrTVFBjjDCwon246Z4": 0.1
    },

    "rewardBeneficiary": "0a05c2d862ca051010698b69b54278cbaf945ccb",

    "multiVersion": true,

    "paymentProcessing": {
        "enabled": false,
        "paymentInterval": 20,
        "minimumPayment": 70,
        "daemon": {
            "host": "127.0.0.1",
            "port": 8332,
            "user": "testuser",
            "password": "testpass"
        }
    },

    "ports": {
        "3008": {
            "diff": 1
        },
        "3032": {
            "diff": 32,
            "varDiff": {
                "minDiff": 8,
                "maxDiff": 512,
                "targetTime": 15,
                "retargetTime": 90,
                "variancePercent": 30
            }
        },
        "3256": {
            "diff": 200000,
            "varDiff": {
                "minDiff": 100000,
                "maxDiff": 2000000,
                "targetTime": 15,
                "retargetTime": 90,
                "variancePercent": 30
            }
         }
    },

    "daemons": [
        {
            "host": "192.168.1.1",
            "port": 8332,
            "user": "testuser",
            "password": "testpass"
        }
    ],

    "p2p": {
        "enabled": false,
        "host": "127.0.0.1",
        "port": 19333,
        "disableTransactions": true
    },

    "mposMode": {
        "enabled": false,
        "host": "127.0.0.1",
        "port": 3306,
        "user": "me",
        "password": "mypass",
        "database": "ltc",
        "checkPassword": true,
        "autoCreateWorker": false
    }

}

